pandoc_static_katex.py
pandoc_static_katex-0.1.3.dist-info/entry_points.txt
pandoc_static_katex-0.1.3.dist-info/LICENSE
pandoc_static_katex-0.1.3.dist-info/WHEEL
pandoc_static_katex-0.1.3.dist-info/METADATA
pandoc_static_katex-0.1.3.dist-info/RECORD
