Metadata-Version: 2.1
Name: pandoc_static_katex
Version: 0.1.3
Summary: A pandoc filter that renders math at build time using KaTeX.
Home-page: https://github.com/Zaharid/pandoc_static_katex
License: UNKNOWN
Author: Zahari Kassabov
Author-email: zk261@cam.ac.uk
Requires-Python: >3.7
Classifier: License :: OSI Approved :: MIT License
Requires-Dist: pandocfilters
